testops/__init__.py
testops/test.py
theamazingtestfirstofitskind-0.0.4.dist-info/METADATA
theamazingtestfirstofitskind-0.0.4.dist-info/WHEEL
theamazingtestfirstofitskind-0.0.4.dist-info/top_level.txt
theamazingtestfirstofitskind-0.0.4.dist-info/RECORD
